odoo/addons/purchase_analytic/README.rst
odoo/addons/purchase_analytic/__init__.py
odoo/addons/purchase_analytic/__manifest__.py
odoo/addons/purchase_analytic/i18n/es.po
odoo/addons/purchase_analytic/i18n/fr.po
odoo/addons/purchase_analytic/i18n/purchase_analytic.pot
odoo/addons/purchase_analytic/models/__init__.py
odoo/addons/purchase_analytic/models/purchase.py
odoo/addons/purchase_analytic/readme/CONTRIBUTORS.rst
odoo/addons/purchase_analytic/readme/DESCRIPTION.rst
odoo/addons/purchase_analytic/readme/HISTORY.rst
odoo/addons/purchase_analytic/static/description/icon.png
odoo/addons/purchase_analytic/static/description/index.html
odoo/addons/purchase_analytic/tests/__init__.py
odoo/addons/purchase_analytic/tests/test_purchase_analytic.py
odoo/addons/purchase_analytic/views/purchase_views.xml
odoo13_addon_purchase_analytic-13.0.3.0.0.dist-info/METADATA
odoo13_addon_purchase_analytic-13.0.3.0.0.dist-info/WHEEL
odoo13_addon_purchase_analytic-13.0.3.0.0.dist-info/top_level.txt
odoo13_addon_purchase_analytic-13.0.3.0.0.dist-info/RECORD
